LICENSE.txt
README.md
setup.py
pyLibrary/__init__.py
pyLibrary/convert.py
pyLibrary/meta.py
pyLibrary/utils.py
pyLibrary.egg-info/PKG-INFO
pyLibrary.egg-info/SOURCES.txt
pyLibrary.egg-info/dependency_links.txt
pyLibrary.egg-info/requires.txt
pyLibrary.egg-info/top_level.txt
pyLibrary/aws/__init__.py
pyLibrary/aws/s3.py
pyLibrary/aws/sqs.py
pyLibrary/env/__init__.py
pyLibrary/env/emailer.py
pyLibrary/env/flask_wrappers.py
pyLibrary/env/git.py
pyLibrary/env/pulse.py