Metadata-Version: 2.1
Name: pyLibrary
Version: 3.264.22338
Summary: Library of Wonderful Things
Home-page: https://github.com/klahnakoski/pyLibrary
Author: Kyle Lahnakoski
Author-email: kyle@lahnakoski.com
License: MPL 2.0
Classifier: Development Status :: 4 - Beta
Classifier: Topic :: Software Development :: Libraries
Classifier: Topic :: Software Development :: Libraries :: Python Modules
Classifier: Programming Language :: Python :: 3.7
Classifier: Programming Language :: Python :: 3.8
Classifier: Programming Language :: Python :: 3.9
Classifier: License :: OSI Approved :: Mozilla Public License 2.0 (MPL 2.0)
Provides-Extra: tests
License-File: LICENSE.txt
